bonepick/__init__.py
bonepick/cli.py
bonepick/logger.py
bonepick/version.py
bonepick/annotate/__init__.py
bonepick/annotate/analysis_loop.py
bonepick/annotate/annotate_loop.py
bonepick/annotate/annotate_utils.py
bonepick/annotate/deluge_utils.py
bonepick/annotate/prompts.py
bonepick/annotate/pydantic_utils.py
bonepick/annotate/prompt_collections/__init__.py
bonepick/annotate/prompt_collections/code_rubrics.py
bonepick/annotate/prompt_collections/sft_filtering.py
bonepick/annotate/prompt_collections/stack_edu_rubrics.py
bonepick/data/__init__.py
bonepick/data/commands.py
bonepick/data/expressions.py
bonepick/data/indentation.py
bonepick/data/normalizers.py
bonepick/data/tokenizers.py
bonepick/data/utils.py
bonepick/evals/__init__.py
bonepick/evals/commands.py
bonepick/evals/display.py
bonepick/evals/modeling.py
bonepick/evals/utils.py
bonepick/fasttext/__init__.py
bonepick/fasttext/commands.py
bonepick/fasttext/utils.py
bonepick/model2vec/__init__.py
bonepick/model2vec/commands.py
bonepick/model2vec/utils.py
bonepick-0.1.0.dist-info/METADATA
bonepick-0.1.0.dist-info/WHEEL
bonepick-0.1.0.dist-info/entry_points.txt
bonepick-0.1.0.dist-info/licenses/LICENSE
bonepick-0.1.0.dist-info/RECORD
