Metadata-Version: 2.4
Name: bonepick
Version: 0.1.0
Summary: CLI tool for training efficient CPU-based text quality classifiers and annotating data for distillation of classifiers.
Author-email: Luca Soldaini <luca@soldaini.net>
License-File: LICENSE
Requires-Python: >=3.12
Requires-Dist: anyascii>=0.3.3
Requires-Dist: backports-weakref>=1.0.post1
Requires-Dist: backports-zstd>=1.2.0
Requires-Dist: click
Requires-Dist: datasets<5,>=4
Requires-Dist: jq>=1.10.0
Requires-Dist: lazy-imports>=1.2.0
Requires-Dist: model2vec[train]>=0.7.0
Requires-Dist: msgspec
Requires-Dist: plsfix>=0.1.8
Requires-Dist: pyyaml>=6.0.3
Requires-Dist: smart-open[s3]>=7.1.0
Requires-Dist: tokenizers>=0.22.1
Requires-Dist: torch>=2.9.1
Requires-Dist: tqdm>=4.66.5
Provides-Extra: annotate
Requires-Dist: fastmcp; extra == 'annotate'
Requires-Dist: lm-deluge<0.1.0,>=0.0.95; extra == 'annotate'
Requires-Dist: platformdirs; extra == 'annotate'
Requires-Dist: pydantic<2.12.0; extra == 'annotate'
Requires-Dist: rich>=13.0.0; extra == 'annotate'
Requires-Dist: scikit-learn>=1.3.0; extra == 'annotate'
Provides-Extra: distill
Requires-Dist: model2vec[distill]>=0.7.0; extra == 'distill'
Requires-Dist: tokenlearn>=0.2.1; extra == 'distill'
